{"GlobalPropertiesHash":"RkX6MjlHLn7clISD3cmTweEjBhYov736n4uR4lKQbNw=","FingerprintPatternsHash":"gq3WsqcKBUGTSNle7RKKyXRIwh7M8ccEqOqYvIzoM04=","PropertyOverridesHash":"8ZRc1sGeVrPBx4lD717BgRaQekyh78QKV9SKsdt638U=","InputHashes":["8vqF3M7RFglvyqnwN5WimKlFyuYQiX4jSKhx99OOgUo=","f5bhHG8XbDJ27rddaTs0dwiRkW61KwaohkGPD9FKdFE=","KJjYAaiRL2hB7nz/Iyi9zmlr1D0GQ6LUJnpVoobANCA=","SlTuL8ioFnFoq9mNxumUmKOksri5Glyn0/Jc23FoG2w="],"CachedAssets":{"8vqF3M7RFglvyqnwN5WimKlFyuYQiX4jSKhx99OOgUo=":{"Identity":"C:\\Users\\Fomka\\Desktop\\backend-core\\ProfileCore\\ProfileCore.UI.Api\\wwwroot\\swagger\\dark-theme.css","SourceId":"ProfileCore.UI.Api","SourceType":"Discovered","ContentRoot":"C:\\Users\\Fomka\\Desktop\\backend-core\\ProfileCore\\ProfileCore.UI.Api\\wwwroot\\","BasePath":"_content/ProfileCore.UI.Api","RelativePath":"swagger/dark-theme#[.{fingerprint}]?.css","AssetKind":"All","AssetMode":"All","AssetRole":"Primary","AssetMergeBehavior":null,"AssetMergeSource":"","RelatedAsset":null,"AssetTraitName":null,"AssetTraitValue":null,"Fingerprint":"0q85qlvmih","Integrity":"aPnP7zVUzgsmc6GCKMf0UwORNqwNvef6ROIfUZJzchY=","CopyToOutputDirectory":"Never","CopyToPublishDirectory":"PreserveNewest","OriginalItemSpec":"wwwroot\\swagger\\dark-theme.css","FileLength":51172,"LastWriteTime":"2025-10-10T15:23:32.2580199+00:00"}},"CachedCopyCandidates":{}}